django_orm_layer/__init__.py
django_orm_layer/utils.py
django_orm_layer/orm/__init__.py
django_orm_layer/orm/manage.py
django_orm_layer/orm/settings.py
django_orm_layer/orm/example_1/__init__.py
django_orm_layer/orm/example_1/models.py
django_orm_layer/orm/example_1/migrations/__init__.py
django_orm_layer/orm/example_2/__init__.py
django_orm_layer/orm/example_2/migrations/__init__.py
django_orm_layer/orm/example_2/models/__init__.py
django_orm_layer/orm/example_2/models/base.py
django_orm_layer/orm/example_2/models/many_to_many.py
django_orm_layer/templates/template_1/__init__.py
django_orm_layer/templates/template_1/models.py
django_orm_layer/templates/template_1/migrations/__init__.py
django_orm_layer/templates/template_2/__init__.py
django_orm_layer/templates/template_2/migrations/__init__.py
django_orm_layer/templates/template_2/models/__init__.py
django_orm_layer/templates/template_2/models/base.py
django_orm_layer/templates/template_2/models/yourmodel.py
django_orm_layer-0.0.7.dist-info/METADATA
django_orm_layer-0.0.7.dist-info/WHEEL
django_orm_layer-0.0.7.dist-info/entry_points.txt
django_orm_layer-0.0.7.dist-info/top_level.txt
django_orm_layer-0.0.7.dist-info/RECORD
