Metadata-Version: 2.1
Name: django-orm-layer
Version: 0.0.7
Summary: django orm layer
Home-page: UNKNOWN
Author: Illyasviel
License: UNKNOWN
Platform: UNKNOWN
Classifier: Topic :: Utilities
Classifier: Programming Language :: Python :: 3.6
Classifier: Programming Language :: Python :: 3.7
Classifier: Programming Language :: Python :: Implementation :: CPython
Classifier: License :: OSI Approved :: MIT License
Requires-Python: >=3.6, <4
Requires-Dist: django (>=1.11)
Requires-Dist: click (>=6.0)
